mcif/__init__.py
mcif/evaluation.py
mcif/io.py
mcif/utils.py
mcif_bench-1.0.dist-info/licenses/LICENSE
mcif_bench-1.0.dist-info/METADATA
mcif_bench-1.0.dist-info/WHEEL
mcif_bench-1.0.dist-info/entry_points.txt
mcif_bench-1.0.dist-info/top_level.txt
mcif_bench-1.0.dist-info/RECORD
