Metadata-Version: 2.4
Name: mcif-bench
Version: 1.0
Summary: Repository with the code for the multilingual and multimodal benchmark MCIF
Author-email: Marco Gaido <mgaido@fbk.eu>, Maike Züfle <maike.zuefle@kit.edu>, Sara Papi <spapi@fbk.eu>
License:    Copyright 2025 FBK, KIT
Project-URL: GitHub, https://github.com/hlt-mt/mcif
Project-URL: Issues, https://github.com/hlt-mt/mcif/issues
Keywords: multimodal,multilingual,benchmark,evaluation
Requires-Python: >=3.9
License-File: LICENSE
Requires-Dist: pyyaml>6.0
Requires-Dist: jiwer==3.0.5
Requires-Dist: bert_score==0.3.13
Requires-Dist: unbabel-comet==2.2.4
Requires-Dist: whisper_normalizer==0.0.10
Provides-Extra: dev
Requires-Dist: flake8; extra == "dev"
Requires-Dist: sphinx; extra == "dev"
Requires-Dist: sphinx-rtd-theme; extra == "dev"
Requires-Dist: build; extra == "dev"
Requires-Dist: twine; extra == "dev"
Dynamic: license-file
